supersql/__init__.py
supersql/alternate.py
supersql/column.py
supersql/constants.py
supersql/core.py
supersql/dquery.py
supersql/helpers.py
supersql/query.py
supersql/results.py
supersql/table.py
supersql-2023.5.11.dist-info/LICENSE.md
supersql-2023.5.11.dist-info/METADATA
supersql-2023.5.11.dist-info/WHEEL
supersql-2023.5.11.dist-info/entry_points.txt
supersql-2023.5.11.dist-info/RECORD
