Metadata-Version: 2.1
Name: supersql
Version: 2023.5.11
Summary: Thin wrapper on top of SQL that enables you write SQL code in python easily
Author: Tersoo Ortserga
Author-email: codesage@live.com
Requires-Python: >=3.7,<4.0
Classifier: Programming Language :: Python :: 3
Classifier: Programming Language :: Python :: 3.7
Classifier: Programming Language :: Python :: 3.8
Classifier: Programming Language :: Python :: 3.9
Classifier: Programming Language :: Python :: 3.10
Classifier: Programming Language :: Python :: 3.11
Provides-Extra: mysql
Provides-Extra: postgres
Provides-Extra: sqlite
Requires-Dist: asyncpg (>=0.27.0,<0.28.0) ; extra == "postgres"
